usody_sanitize/__init__.py
usody_sanitize/cmd_client.py
usody_sanitize/commands.py
usody_sanitize/config.py
usody_sanitize/erasure.py
usody_sanitize/exceptions.py
usody_sanitize/methods.py
usody_sanitize/sanitize.py
usody_sanitize/schemas/__init__.py
usody_sanitize/schemas/definition.py
usody_sanitize/schemas/devices.py
usody_sanitize/schemas/export_data.py
usody_sanitize/schemas/sanitize.py
usody_sanitize/steps.py
usody_sanitize/utils.py
usody_sanitize-0.1.3b4.dist-info/LICENSE
usody_sanitize-0.1.3b4.dist-info/METADATA
usody_sanitize-0.1.3b4.dist-info/WHEEL
usody_sanitize-0.1.3b4.dist-info/entry_points.txt
usody_sanitize-0.1.3b4.dist-info/RECORD
