Metadata-Version: 2.1
Name: usody-sanitize
Version: 0.1.3b4
Summary: A tool to securely erase/wipe data on disks HDD and SSD with a proper sanitization process.
Home-page: https://github.com/usody/sanitize
License: GNU
Author: blkpws
Author-email: me@blkpws.xyz
Requires-Python: >=3.8,<4.0
Classifier: License :: Other/Proprietary License
Classifier: Programming Language :: Python :: 3
Classifier: Programming Language :: Python :: 3.8
Classifier: Programming Language :: Python :: 3.9
Classifier: Programming Language :: Python :: 3.10
Classifier: Programming Language :: Python :: 3.11
Classifier: Programming Language :: Python :: 3.12
Requires-Dist: pydantic (>=2,<3)
Requires-Dist: pydantic-settings (>=2.1.0,<3.0.0)
Project-URL: Repository, https://github.com/usody/sanitize
